LICENSE
setup.py
HiLineToJuicer/__init__.py
HiLineToJuicer/main.py
HiLineToJuicer.egg-info/PKG-INFO
HiLineToJuicer.egg-info/SOURCES.txt
HiLineToJuicer.egg-info/dependency_links.txt
HiLineToJuicer.egg-info/entry_points.txt
HiLineToJuicer.egg-info/requires.txt
HiLineToJuicer.egg-info/top_level.txt