Metadata-Version: 2.1
Name: HiLineToJuicer
Version: 0.0.2
Summary: Convert HiLine SAM alignments to Juicer format
Home-page: UNKNOWN
Author: Ed Harry
Author-email: edward.harry@sanger.ac.uk
License: UNKNOWN
Platform: UNKNOWN
Requires-Python: >=3.8.0
License-File: LICENSE
